uw_r25/VERSION
uw_r25/__init__.py
uw_r25/dao.py
uw_r25/events.py
uw_r25/models.py
uw_r25/reservations.py
uw_r25/spaces.py
uw_r25/test.py
uw_r25/resources/r25/file/r25ws/servlet/wrd/run/event.xml_event_id_100000
uw_r25/resources/r25/file/r25ws/servlet/wrd/run/event.xml_event_id_100002
uw_r25/resources/r25/file/r25ws/servlet/wrd/run/events.xml
uw_r25/resources/r25/file/r25ws/servlet/wrd/run/events.xml_parent_id_100000
uw_r25/resources/r25/file/r25ws/servlet/wrd/run/events.xml_parent_id_100002
uw_r25/resources/r25/file/r25ws/servlet/wrd/run/space.xml_space_id_1000
uw_r25/resources/r25/file/r25ws/servlet/wrd/run/spaces.xml
uw_r25/tests/__init__.py
uw_r25/tests/test_dao.py
uw_r25/tests/test_events.py
uw_r25/tests/test_reservations.py
uw_r25/tests/test_spaces.py
uw_r25/util/__init__.py
UW_RestClients_R25-0.5.dist-info/LICENSE
UW_RestClients_R25-0.5.dist-info/METADATA
UW_RestClients_R25-0.5.dist-info/WHEEL
UW_RestClients_R25-0.5.dist-info/top_level.txt
UW_RestClients_R25-0.5.dist-info/RECORD
