Metadata-Version: 2.1
Name: UW-RestClients-R25
Version: 0.5
Summary: A library for connecting to the UW R25 API
Home-page: https://github.com/uw-it-aca/uw-restclients-r25
Author: UW-IT T&LS
Author-email: aca-it@uw.edu
License: Apache License, Version 2.0
Classifier: Intended Audience :: Developers
Classifier: License :: OSI Approved :: Apache Software License
Classifier: Operating System :: OS Independent
Classifier: Programming Language :: Python
License-File: LICENSE
Requires-Dist: UW-RestClients-Core
Requires-Dist: lxml <5
